azure/monitor/opentelemetry/__init__.py
azure/monitor/opentelemetry/_configure.py
azure/monitor/opentelemetry/_constants.py
azure/monitor/opentelemetry/_types.py
azure/monitor/opentelemetry/_version.py
azure/monitor/opentelemetry/py.typed
azure/monitor/opentelemetry/_autoinstrumentation/__init__.py
azure/monitor/opentelemetry/_autoinstrumentation/configurator.py
azure/monitor/opentelemetry/_autoinstrumentation/distro.py
azure/monitor/opentelemetry/_diagnostics/__init__.py
azure/monitor/opentelemetry/_diagnostics/diagnostic_logging.py
azure/monitor/opentelemetry/_diagnostics/status_logger.py
azure/monitor/opentelemetry/_utils/__init__.py
azure/monitor/opentelemetry/_utils/configurations.py
azure/monitor/opentelemetry/_utils/instrumentation.py
azure_monitor_opentelemetry-1.8.0.dist-info/licenses/LICENSE
azure_monitor_opentelemetry-1.8.0.dist-info/licenses/NOTICE.txt
azure_monitor_opentelemetry-1.8.0.dist-info/METADATA
azure_monitor_opentelemetry-1.8.0.dist-info/WHEEL
azure_monitor_opentelemetry-1.8.0.dist-info/entry_points.txt
azure_monitor_opentelemetry-1.8.0.dist-info/top_level.txt
azure_monitor_opentelemetry-1.8.0.dist-info/RECORD
