Metadata-Version: 2.4
Name: azure-monitor-opentelemetry
Version: 1.8.0
Summary: Microsoft Azure Monitor Opentelemetry Distro Client Library for Python
Home-page: https://github.com/Azure/azure-sdk-for-python/tree/main/sdk/monitor/azure-monitor-opentelemetry
Author: Microsoft Corporation
Author-email: ascl@microsoft.com
License: MIT License
Keywords: azure,azure sdk
Classifier: Development Status :: 5 - Production/Stable
Classifier: Intended Audience :: Developers
Classifier: Programming Language :: Python
Classifier: Programming Language :: Python :: 3
Classifier: Programming Language :: Python :: 3.9
Classifier: Programming Language :: Python :: 3.10
Classifier: Programming Language :: Python :: 3.11
Classifier: Programming Language :: Python :: 3.12
Classifier: License :: OSI Approved :: MIT License
Requires-Python: >=3.8
License-File: LICENSE
License-File: NOTICE.txt
Requires-Dist: azure-core<2.0.0,>=1.28.0
Requires-Dist: azure-core-tracing-opentelemetry~=1.0.0b11
Requires-Dist: azure-monitor-opentelemetry-exporter~=1.0.0b41
Requires-Dist: opentelemetry-instrumentation-django~=0.57b0
Requires-Dist: opentelemetry-instrumentation-fastapi~=0.57b0
Requires-Dist: opentelemetry-instrumentation-flask~=0.57b0
Requires-Dist: opentelemetry-instrumentation-psycopg2~=0.57b0
Requires-Dist: opentelemetry-instrumentation-requests~=0.57b0
Requires-Dist: opentelemetry-instrumentation-urllib~=0.57b0
Requires-Dist: opentelemetry-instrumentation-urllib3~=0.57b0
Requires-Dist: opentelemetry-resource-detector-azure~=0.1.5
Requires-Dist: opentelemetry-sdk~=1.36.0
Dynamic: author
Dynamic: author-email
Dynamic: classifier
Dynamic: description
Dynamic: description-content-type
Dynamic: home-page
Dynamic: keywords
Dynamic: license
Dynamic: license-file
Dynamic: requires-dist
Dynamic: requires-python
Dynamic: summary
